[{
  "_id": {
    "$oid": "6818a999bca891e0fc129492"
  },
  "user_id": {
    "$oid": "6818a997893db3ac0ac03857"
  },
  "movie_id": {
    "$oid": "6818a999bca891e0fc129484"
  },
  "added_date": {
    "$date": "2025-04-16T15:07:54.497Z"
  }
},
{
  "_id": {
    "$oid": "6818a999bca891e0fc129493"
  },
  "user_id": {
    "$oid": "6818a997893db3ac0ac03857"
  },
  "movie_id": {
    "$oid": "6818a999bca891e0fc12948b"
  },
  "added_date": {
    "$date": "2025-03-19T18:56:41.497Z"
  }
},
{
  "_id": {
    "$oid": "6818a999bca891e0fc129494"
  },
  "user_id": {
    "$oid": "6818a997893db3ac0ac03857"
  },
  "movie_id": {
    "$oid": "6818a999bca891e0fc129491"
  },
  "added_date": {
    "$date": "2025-04-10T09:06:38.497Z"
  }
},
{
  "_id": {
    "$oid": "6818a999bca891e0fc129495"
  },
  "user_id": {
    "$oid": "6818a997893db3ac0ac03858"
  },
  "movie_id": {
    "$oid": "6818a999bca891e0fc129480"
  },
  "added_date": {
    "$date": "2025-03-19T13:01:17.497Z"
  }
},
{
  "_id": {
    "$oid": "6818a999bca891e0fc129496"
  },
  "user_id": {
    "$oid": "6818a997893db3ac0ac03859"
  },
  "movie_id": {
    "$oid": "6818a999bca891e0fc129481"
  },
  "added_date": {
    "$date": "2025-04-25T21:33:17.497Z"
  }
},
{
  "_id": {
    "$oid": "6818a999bca891e0fc129497"
  },
  "user_id": {
    "$oid": "6818a997893db3ac0ac0385a"
  },
  "movie_id": {
    "$oid": "6818a999bca891e0fc12948b"
  },
  "added_date": {
    "$date": "2025-04-03T16:37:39.497Z"
  }
},
{
  "_id": {
    "$oid": "6818a999bca891e0fc129498"
  },
  "user_id": {
    "$oid": "6818a997893db3ac0ac0385a"
  },
  "movie_id": {
    "$oid": "6818a999bca891e0fc129489"
  },
  "added_date": {
    "$date": "2025-04-24T17:27:51.497Z"
  }
},
{
  "_id": {
    "$oid": "6818a999bca891e0fc129499"
  },
  "user_id": {
    "$oid": "6818a997893db3ac0ac0385b"
  },
  "movie_id": {
    "$oid": "6818a999bca891e0fc129490"
  },
  "added_date": {
    "$date": "2025-05-01T06:59:41.497Z"
  }
},
{
  "_id": {
    "$oid": "6818a999bca891e0fc12949a"
  },
  "user_id": {
    "$oid": "6818a997893db3ac0ac0385b"
  },
  "movie_id": {
    "$oid": "6818a999bca891e0fc12948c"
  },
  "added_date": {
    "$date": "2025-03-24T16:31:53.497Z"
  }
},
{
  "_id": {
    "$oid": "6818a999bca891e0fc12949b"
  },
  "user_id": {
    "$oid": "6818a997893db3ac0ac0385b"
  },
  "movie_id": {
    "$oid": "6818a999bca891e0fc12948a"
  },
  "added_date": {
    "$date": "2025-04-29T17:55:26.497Z"
  }
},
{
  "_id": {
    "$oid": "6818a999bca891e0fc12949c"
  },
  "user_id": {
    "$oid": "6818a997893db3ac0ac0385c"
  },
  "movie_id": {
    "$oid": "6818a999bca891e0fc129490"
  },
  "added_date": {
    "$date": "2025-04-01T13:22:39.497Z"
  }
},
{
  "_id": {
    "$oid": "6818a999bca891e0fc12949d"
  },
  "user_id": {
    "$oid": "6818a997893db3ac0ac0385c"
  },
  "movie_id": {
    "$oid": "6818a999bca891e0fc12948a"
  },
  "added_date": {
    "$date": "2025-03-19T23:45:02.497Z"
  }
},
{
  "_id": {
    "$oid": "6818a999bca891e0fc12949e"
  },
  "user_id": {
    "$oid": "6818a997893db3ac0ac0385c"
  },
  "movie_id": {
    "$oid": "6818a999bca891e0fc129487"
  },
  "added_date": {
    "$date": "2025-04-13T06:25:34.497Z"
  }
},
{
  "_id": {
    "$oid": "6818a999bca891e0fc12949f"
  },
  "user_id": {
    "$oid": "6818a997893db3ac0ac0385e"
  },
  "movie_id": {
    "$oid": "6818a999bca891e0fc129481"
  },
  "added_date": {
    "$date": "2025-03-28T07:31:39.497Z"
  }
},
{
  "_id": {
    "$oid": "6818a999bca891e0fc1294a0"
  },
  "user_id": {
    "$oid": "6818a997893db3ac0ac0385e"
  },
  "movie_id": {
    "$oid": "6818a999bca891e0fc129482"
  },
  "added_date": {
    "$date": "2025-03-25T07:32:06.497Z"
  }
},
{
  "_id": {
    "$oid": "6818a999bca891e0fc1294a1"
  },
  "user_id": {
    "$oid": "6818a997893db3ac0ac0385f"
  },
  "movie_id": {
    "$oid": "6818a999bca891e0fc129489"
  },
  "added_date": {
    "$date": "2025-04-05T01:31:53.497Z"
  }
},
{
  "_id": {
    "$oid": "6818a999bca891e0fc1294a2"
  },
  "user_id": {
    "$oid": "6818a997893db3ac0ac0385f"
  },
  "movie_id": {
    "$oid": "6818a999bca891e0fc129487"
  },
  "added_date": {
    "$date": "2025-03-07T20:20:45.497Z"
  }
},
{
  "_id": {
    "$oid": "6818a999bca891e0fc1294a3"
  },
  "user_id": {
    "$oid": "6818a997893db3ac0ac0385f"
  },
  "movie_id": {
    "$oid": "6818a999bca891e0fc129481"
  },
  "added_date": {
    "$date": "2025-03-29T23:40:25.497Z"
  }
},
{
  "_id": {
    "$oid": "6818a999bca891e0fc1294a4"
  },
  "user_id": {
    "$oid": "6818a997893db3ac0ac03860"
  },
  "movie_id": {
    "$oid": "6818a999bca891e0fc129485"
  },
  "added_date": {
    "$date": "2025-04-01T12:56:32.497Z"
  }
},
{
  "_id": {
    "$oid": "6818a999bca891e0fc1294a5"
  },
  "user_id": {
    "$oid": "6818a997893db3ac0ac03862"
  },
  "movie_id": {
    "$oid": "6818a999bca891e0fc12948c"
  },
  "added_date": {
    "$date": "2025-04-15T10:22:32.497Z"
  }
},
{
  "_id": {
    "$oid": "6818a999bca891e0fc1294a6"
  },
  "user_id": {
    "$oid": "6818a997893db3ac0ac03863"
  },
  "movie_id": {
    "$oid": "6818a999bca891e0fc129486"
  },
  "added_date": {
    "$date": "2025-03-11T03:35:47.497Z"
  }
},
{
  "_id": {
    "$oid": "6818a999bca891e0fc1294a7"
  },
  "user_id": {
    "$oid": "6818a997893db3ac0ac03863"
  },
  "movie_id": {
    "$oid": "6818a999bca891e0fc12948b"
  },
  "added_date": {
    "$date": "2025-03-21T17:36:34.497Z"
  }
},
{
  "_id": {
    "$oid": "6818a999bca891e0fc1294a8"
  },
  "user_id": {
    "$oid": "6818a997893db3ac0ac03863"
  },
  "movie_id": {
    "$oid": "6818a999bca891e0fc129487"
  },
  "added_date": {
    "$date": "2025-04-28T06:28:31.497Z"
  }
},
{
  "_id": {
    "$oid": "6818a999bca891e0fc1294a9"
  },
  "user_id": {
    "$oid": "6818a997893db3ac0ac03864"
  },
  "movie_id": {
    "$oid": "6818a999bca891e0fc12947e"
  },
  "added_date": {
    "$date": "2025-04-26T11:24:29.497Z"
  }
},
{
  "_id": {
    "$oid": "6818a999bca891e0fc1294aa"
  },
  "user_id": {
    "$oid": "6818a997893db3ac0ac03864"
  },
  "movie_id": {
    "$oid": "6818a999bca891e0fc129488"
  },
  "added_date": {
    "$date": "2025-04-11T04:35:40.497Z"
  }
},
{
  "_id": {
    "$oid": "6818a999bca891e0fc1294ab"
  },
  "user_id": {
    "$oid": "6818a997893db3ac0ac03864"
  },
  "movie_id": {
    "$oid": "6818a999bca891e0fc129490"
  },
  "added_date": {
    "$date": "2025-04-04T22:39:27.497Z"
  }
},
{
  "_id": {
    "$oid": "6818a999bca891e0fc1294ac"
  },
  "user_id": {
    "$oid": "6818a997893db3ac0ac03865"
  },
  "movie_id": {
    "$oid": "6818a999bca891e0fc12948a"
  },
  "added_date": {
    "$date": "2025-04-26T14:39:34.497Z"
  }
},
{
  "_id": {
    "$oid": "6818a999bca891e0fc1294ad"
  },
  "user_id": {
    "$oid": "6818a997893db3ac0ac03865"
  },
  "movie_id": {
    "$oid": "6818a999bca891e0fc129483"
  },
  "added_date": {
    "$date": "2025-03-14T12:50:20.497Z"
  }
},
{
  "_id": {
    "$oid": "6818a999bca891e0fc1294ae"
  },
  "user_id": {
    "$oid": "6818a997893db3ac0ac03866"
  },
  "movie_id": {
    "$oid": "6818a999bca891e0fc12948f"
  },
  "added_date": {
    "$date": "2025-04-19T02:57:24.497Z"
  }
},
{
  "_id": {
    "$oid": "6818a999bca891e0fc1294af"
  },
  "user_id": {
    "$oid": "6818a997893db3ac0ac03866"
  },
  "movie_id": {
    "$oid": "6818a999bca891e0fc129488"
  },
  "added_date": {
    "$date": "2025-03-30T15:21:58.497Z"
  }
},
{
  "_id": {
    "$oid": "6818a999bca891e0fc1294b0"
  },
  "user_id": {
    "$oid": "6818a997893db3ac0ac03866"
  },
  "movie_id": {
    "$oid": "6818a999bca891e0fc12947f"
  },
  "added_date": {
    "$date": "2025-05-06T15:08:17.497Z"
  }
},
{
  "_id": {
    "$oid": "6818a999bca891e0fc1294b1"
  },
  "user_id": {
    "$oid": "6818a997893db3ac0ac03867"
  },
  "movie_id": {
    "$oid": "6818a999bca891e0fc129489"
  },
  "added_date": {
    "$date": "2025-04-29T18:28:07.497Z"
  }
},
{
  "_id": {
    "$oid": "6818a999bca891e0fc1294b2"
  },
  "user_id": {
    "$oid": "6818a997893db3ac0ac03867"
  },
  "movie_id": {
    "$oid": "6818a999bca891e0fc129482"
  },
  "added_date": {
    "$date": "2025-03-15T04:37:21.497Z"
  }
},
{
  "_id": {
    "$oid": "6818a999bca891e0fc1294b3"
  },
  "user_id": {
    "$oid": "6818a997893db3ac0ac03868"
  },
  "movie_id": {
    "$oid": "6818a999bca891e0fc129483"
  },
  "added_date": {
    "$date": "2025-04-12T04:22:31.497Z"
  }
},
{
  "_id": {
    "$oid": "6818a999bca891e0fc1294b4"
  },
  "user_id": {
    "$oid": "6818a997893db3ac0ac0386b"
  },
  "movie_id": {
    "$oid": "6818a999bca891e0fc12948a"
  },
  "added_date": {
    "$date": "2025-04-02T13:39:52.497Z"
  }
},
{
  "_id": {
    "$oid": "6818a999bca891e0fc1294b5"
  },
  "user_id": {
    "$oid": "6818a997893db3ac0ac0386b"
  },
  "movie_id": {
    "$oid": "6818a999bca891e0fc129480"
  },
  "added_date": {
    "$date": "2025-03-18T14:47:21.497Z"
  }
},
{
  "_id": {
    "$oid": "6818a999bca891e0fc1294b6"
  },
  "user_id": {
    "$oid": "6818a997893db3ac0ac0386b"
  },
  "movie_id": {
    "$oid": "6818a999bca891e0fc129490"
  },
  "added_date": {
    "$date": "2025-03-24T02:33:13.497Z"
  }
},
{
  "_id": {
    "$oid": "6818a999bca891e0fc1294b7"
  },
  "user_id": {
    "$oid": "6818a997893db3ac0ac0386e"
  },
  "movie_id": {
    "$oid": "6818a999bca891e0fc129486"
  },
  "added_date": {
    "$date": "2025-03-09T18:23:11.497Z"
  }
},
{
  "_id": {
    "$oid": "6818a999bca891e0fc1294b8"
  },
  "user_id": {
    "$oid": "6818a997893db3ac0ac0386f"
  },
  "movie_id": {
    "$oid": "6818a999bca891e0fc12948a"
  },
  "added_date": {
    "$date": "2025-04-27T23:17:00.497Z"
  }
},
{
  "_id": {
    "$oid": "6818a999bca891e0fc1294b9"
  },
  "user_id": {
    "$oid": "6818a997893db3ac0ac03871"
  },
  "movie_id": {
    "$oid": "6818a999bca891e0fc12948a"
  },
  "added_date": {
    "$date": "2025-03-10T13:01:06.497Z"
  }
},
{
  "_id": {
    "$oid": "6818a999bca891e0fc1294ba"
  },
  "user_id": {
    "$oid": "6818a997893db3ac0ac03871"
  },
  "movie_id": {
    "$oid": "6818a999bca891e0fc12948b"
  },
  "added_date": {
    "$date": "2025-04-04T12:34:14.497Z"
  }
},
{
  "_id": {
    "$oid": "6818a999bca891e0fc1294bb"
  },
  "user_id": {
    "$oid": "6818a997893db3ac0ac03872"
  },
  "movie_id": {
    "$oid": "6818a999bca891e0fc12948a"
  },
  "added_date": {
    "$date": "2025-03-07T16:00:23.497Z"
  }
},
{
  "_id": {
    "$oid": "6818a999bca891e0fc1294bc"
  },
  "user_id": {
    "$oid": "6818a997893db3ac0ac03872"
  },
  "movie_id": {
    "$oid": "6818a999bca891e0fc12947f"
  },
  "added_date": {
    "$date": "2025-04-02T01:18:01.497Z"
  }
},
{
  "_id": {
    "$oid": "6818a999bca891e0fc1294bd"
  },
  "user_id": {
    "$oid": "6818a997893db3ac0ac03873"
  },
  "movie_id": {
    "$oid": "6818a999bca891e0fc12948b"
  },
  "added_date": {
    "$date": "2025-03-20T18:03:09.497Z"
  }
},
{
  "_id": {
    "$oid": "6818a999bca891e0fc1294be"
  },
  "user_id": {
    "$oid": "6818a997893db3ac0ac03873"
  },
  "movie_id": {
    "$oid": "6818a999bca891e0fc12947f"
  },
  "added_date": {
    "$date": "2025-04-10T03:13:39.497Z"
  }
},
{
  "_id": {
    "$oid": "6818a999bca891e0fc1294bf"
  },
  "user_id": {
    "$oid": "6818a997893db3ac0ac03875"
  },
  "movie_id": {
    "$oid": "6818a999bca891e0fc129481"
  },
  "added_date": {
    "$date": "2025-04-13T01:31:26.497Z"
  }
},
{
  "_id": {
    "$oid": "6818a999bca891e0fc1294c0"
  },
  "user_id": {
    "$oid": "6818a997893db3ac0ac03875"
  },
  "movie_id": {
    "$oid": "6818a999bca891e0fc12948c"
  },
  "added_date": {
    "$date": "2025-04-02T14:34:53.497Z"
  }
},
{
  "_id": {
    "$oid": "6818a999bca891e0fc1294c1"
  },
  "user_id": {
    "$oid": "6818a997893db3ac0ac03876"
  },
  "movie_id": {
    "$oid": "6818a999bca891e0fc129486"
  },
  "added_date": {
    "$date": "2025-04-18T03:04:22.497Z"
  }
},
{
  "_id": {
    "$oid": "6818a999bca891e0fc1294c2"
  },
  "user_id": {
    "$oid": "6818a997893db3ac0ac03876"
  },
  "movie_id": {
    "$oid": "6818a999bca891e0fc129488"
  },
  "added_date": {
    "$date": "2025-04-04T08:53:41.497Z"
  }
},
{
  "_id": {
    "$oid": "6818a999bca891e0fc1294c3"
  },
  "user_id": {
    "$oid": "6818a997893db3ac0ac03877"
  },
  "movie_id": {
    "$oid": "6818a999bca891e0fc129488"
  },
  "added_date": {
    "$date": "2025-04-23T04:46:58.497Z"
  }
},
{
  "_id": {
    "$oid": "6818a999bca891e0fc1294c4"
  },
  "user_id": {
    "$oid": "6818a997893db3ac0ac03877"
  },
  "movie_id": {
    "$oid": "6818a999bca891e0fc12948a"
  },
  "added_date": {
    "$date": "2025-04-09T21:21:16.497Z"
  }
},
{
  "_id": {
    "$oid": "6818a999bca891e0fc1294c5"
  },
  "user_id": {
    "$oid": "6818a997893db3ac0ac03878"
  },
  "movie_id": {
    "$oid": "6818a999bca891e0fc129485"
  },
  "added_date": {
    "$date": "2025-03-23T05:31:12.497Z"
  }
},
{
  "_id": {
    "$oid": "6818a999bca891e0fc1294c6"
  },
  "user_id": {
    "$oid": "6818a997893db3ac0ac03879"
  },
  "movie_id": {
    "$oid": "6818a999bca891e0fc12948e"
  },
  "added_date": {
    "$date": "2025-03-20T08:34:27.497Z"
  }
},
{
  "_id": {
    "$oid": "6818a999bca891e0fc1294c7"
  },
  "user_id": {
    "$oid": "6818a997893db3ac0ac0387a"
  },
  "movie_id": {
    "$oid": "6818a999bca891e0fc12948c"
  },
  "added_date": {
    "$date": "2025-05-04T02:01:13.497Z"
  }
},
{
  "_id": {
    "$oid": "6818a999bca891e0fc1294c8"
  },
  "user_id": {
    "$oid": "6818a997893db3ac0ac0387a"
  },
  "movie_id": {
    "$oid": "6818a999bca891e0fc129486"
  },
  "added_date": {
    "$date": "2025-03-13T03:51:26.497Z"
  }
},
{
  "_id": {
    "$oid": "6818a999bca891e0fc1294c9"
  },
  "user_id": {
    "$oid": "6818a997893db3ac0ac0387a"
  },
  "movie_id": {
    "$oid": "6818a999bca891e0fc129491"
  },
  "added_date": {
    "$date": "2025-05-01T09:39:32.497Z"
  }
},
{
  "_id": {
    "$oid": "6818a999bca891e0fc1294ca"
  },
  "user_id": {
    "$oid": "6818a997893db3ac0ac0387b"
  },
  "movie_id": {
    "$oid": "6818a999bca891e0fc129485"
  },
  "added_date": {
    "$date": "2025-03-07T12:26:55.497Z"
  }
},
{
  "_id": {
    "$oid": "6818a999bca891e0fc1294cb"
  },
  "user_id": {
    "$oid": "6818a997893db3ac0ac0387b"
  },
  "movie_id": {
    "$oid": "6818a999bca891e0fc129482"
  },
  "added_date": {
    "$date": "2025-03-25T09:44:50.497Z"
  }
},
{
  "_id": {
    "$oid": "6818a999bca891e0fc1294cc"
  },
  "user_id": {
    "$oid": "6818a997893db3ac0ac0387c"
  },
  "movie_id": {
    "$oid": "6818a999bca891e0fc12947e"
  },
  "added_date": {
    "$date": "2025-04-13T22:44:07.497Z"
  }
},
{
  "_id": {
    "$oid": "6818a999bca891e0fc1294cd"
  },
  "user_id": {
    "$oid": "6818a997893db3ac0ac0387c"
  },
  "movie_id": {
    "$oid": "6818a999bca891e0fc129483"
  },
  "added_date": {
    "$date": "2025-03-21T02:10:22.497Z"
  }
},
{
  "_id": {
    "$oid": "6818a999bca891e0fc1294ce"
  },
  "user_id": {
    "$oid": "6818a997893db3ac0ac0387c"
  },
  "movie_id": {
    "$oid": "6818a999bca891e0fc12947f"
  },
  "added_date": {
    "$date": "2025-03-15T11:17:59.497Z"
  }
},
{
  "_id": {
    "$oid": "6818a999bca891e0fc1294cf"
  },
  "user_id": {
    "$oid": "6818a997893db3ac0ac0387d"
  },
  "movie_id": {
    "$oid": "6818a999bca891e0fc12947e"
  },
  "added_date": {
    "$date": "2025-04-02T10:33:12.497Z"
  }
},
{
  "_id": {
    "$oid": "6818a999bca891e0fc1294d0"
  },
  "user_id": {
    "$oid": "6818a997893db3ac0ac0387d"
  },
  "movie_id": {
    "$oid": "6818a999bca891e0fc129487"
  },
  "added_date": {
    "$date": "2025-05-01T13:28:07.497Z"
  }
},
{
  "_id": {
    "$oid": "6818a999bca891e0fc1294d1"
  },
  "user_id": {
    "$oid": "6818a997893db3ac0ac0387e"
  },
  "movie_id": {
    "$oid": "6818a999bca891e0fc129489"
  },
  "added_date": {
    "$date": "2025-04-21T00:05:50.497Z"
  }
},
{
  "_id": {
    "$oid": "6818a999bca891e0fc1294d2"
  },
  "user_id": {
    "$oid": "6818a997893db3ac0ac0387e"
  },
  "movie_id": {
    "$oid": "6818a999bca891e0fc129484"
  },
  "added_date": {
    "$date": "2025-03-29T21:21:34.497Z"
  }
},
{
  "_id": {
    "$oid": "6818a999bca891e0fc1294d3"
  },
  "user_id": {
    "$oid": "6818a997893db3ac0ac0387e"
  },
  "movie_id": {
    "$oid": "6818a999bca891e0fc12947f"
  },
  "added_date": {
    "$date": "2025-04-18T00:21:16.497Z"
  }
},
{
  "_id": {
    "$oid": "6818a999bca891e0fc1294d4"
  },
  "user_id": {
    "$oid": "6818a997893db3ac0ac0387f"
  },
  "movie_id": {
    "$oid": "6818a999bca891e0fc12947f"
  },
  "added_date": {
    "$date": "2025-03-12T01:03:26.497Z"
  }
},
{
  "_id": {
    "$oid": "6818a999bca891e0fc1294d5"
  },
  "user_id": {
    "$oid": "6818a997893db3ac0ac0387f"
  },
  "movie_id": {
    "$oid": "6818a999bca891e0fc129486"
  },
  "added_date": {
    "$date": "2025-05-01T13:27:08.497Z"
  }
},
{
  "_id": {
    "$oid": "6818a999bca891e0fc1294d6"
  },
  "user_id": {
    "$oid": "6818a997893db3ac0ac0387f"
  },
  "movie_id": {
    "$oid": "6818a999bca891e0fc129488"
  },
  "added_date": {
    "$date": "2025-03-09T11:22:16.497Z"
  }
},
{
  "_id": {
    "$oid": "6818a999bca891e0fc1294d7"
  },
  "user_id": {
    "$oid": "6818a997893db3ac0ac03880"
  },
  "movie_id": {
    "$oid": "6818a999bca891e0fc129490"
  },
  "added_date": {
    "$date": "2025-04-07T14:44:50.497Z"
  }
},
{
  "_id": {
    "$oid": "6818a999bca891e0fc1294d8"
  },
  "user_id": {
    "$oid": "6818a997893db3ac0ac03880"
  },
  "movie_id": {
    "$oid": "6818a999bca891e0fc12947e"
  },
  "added_date": {
    "$date": "2025-03-25T15:32:17.497Z"
  }
},
{
  "_id": {
    "$oid": "6818a999bca891e0fc1294d9"
  },
  "user_id": {
    "$oid": "6818a997893db3ac0ac03881"
  },
  "movie_id": {
    "$oid": "6818a999bca891e0fc12947e"
  },
  "added_date": {
    "$date": "2025-04-30T11:50:40.497Z"
  }
},
{
  "_id": {
    "$oid": "6818a999bca891e0fc1294da"
  },
  "user_id": {
    "$oid": "6818a997893db3ac0ac03882"
  },
  "movie_id": {
    "$oid": "6818a999bca891e0fc12947e"
  },
  "added_date": {
    "$date": "2025-04-04T04:03:40.497Z"
  }
},
{
  "_id": {
    "$oid": "6818a999bca891e0fc1294db"
  },
  "user_id": {
    "$oid": "6818a997893db3ac0ac03882"
  },
  "movie_id": {
    "$oid": "6818a999bca891e0fc12947f"
  },
  "added_date": {
    "$date": "2025-03-07T04:39:00.497Z"
  }
},
{
  "_id": {
    "$oid": "6818a999bca891e0fc1294dc"
  },
  "user_id": {
    "$oid": "6818a997893db3ac0ac03882"
  },
  "movie_id": {
    "$oid": "6818a999bca891e0fc129490"
  },
  "added_date": {
    "$date": "2025-04-26T04:18:27.497Z"
  }
},
{
  "_id": {
    "$oid": "6818a999bca891e0fc1294dd"
  },
  "user_id": {
    "$oid": "6818a997893db3ac0ac03883"
  },
  "movie_id": {
    "$oid": "6818a999bca891e0fc129484"
  },
  "added_date": {
    "$date": "2025-03-06T21:09:37.497Z"
  }
},
{
  "_id": {
    "$oid": "6818a999bca891e0fc1294de"
  },
  "user_id": {
    "$oid": "6818a997893db3ac0ac03883"
  },
  "movie_id": {
    "$oid": "6818a999bca891e0fc12948c"
  },
  "added_date": {
    "$date": "2025-04-04T03:01:06.497Z"
  }
},
{
  "_id": {
    "$oid": "6818a999bca891e0fc1294df"
  },
  "user_id": {
    "$oid": "6818a997893db3ac0ac03884"
  },
  "movie_id": {
    "$oid": "6818a999bca891e0fc129486"
  },
  "added_date": {
    "$date": "2025-04-09T06:00:29.497Z"
  }
},
{
  "_id": {
    "$oid": "6818a999bca891e0fc1294e0"
  },
  "user_id": {
    "$oid": "6818a997893db3ac0ac03884"
  },
  "movie_id": {
    "$oid": "6818a999bca891e0fc129490"
  },
  "added_date": {
    "$date": "2025-05-06T04:01:21.497Z"
  }
},
{
  "_id": {
    "$oid": "6818a999bca891e0fc1294e1"
  },
  "user_id": {
    "$oid": "6818a997893db3ac0ac03884"
  },
  "movie_id": {
    "$oid": "6818a999bca891e0fc129485"
  },
  "added_date": {
    "$date": "2025-03-24T16:52:05.497Z"
  }
},
{
  "_id": {
    "$oid": "6818a999bca891e0fc1294e2"
  },
  "user_id": {
    "$oid": "6818a997893db3ac0ac03886"
  },
  "movie_id": {
    "$oid": "6818a999bca891e0fc129491"
  },
  "added_date": {
    "$date": "2025-04-10T07:11:27.497Z"
  }
},
{
  "_id": {
    "$oid": "6818a999bca891e0fc1294e3"
  },
  "user_id": {
    "$oid": "6818a997893db3ac0ac03886"
  },
  "movie_id": {
    "$oid": "6818a999bca891e0fc12947f"
  },
  "added_date": {
    "$date": "2025-04-18T20:53:54.497Z"
  }
},
{
  "_id": {
    "$oid": "6818a999bca891e0fc1294e4"
  },
  "user_id": {
    "$oid": "6818a997893db3ac0ac03886"
  },
  "movie_id": {
    "$oid": "6818a999bca891e0fc129482"
  },
  "added_date": {
    "$date": "2025-03-21T10:52:01.497Z"
  }
},
{
  "_id": {
    "$oid": "6818a999bca891e0fc1294e5"
  },
  "user_id": {
    "$oid": "6818a997893db3ac0ac03887"
  },
  "movie_id": {
    "$oid": "6818a999bca891e0fc129483"
  },
  "added_date": {
    "$date": "2025-04-11T23:49:25.497Z"
  }
},
{
  "_id": {
    "$oid": "6818a999bca891e0fc1294e6"
  },
  "user_id": {
    "$oid": "6818a997893db3ac0ac03888"
  },
  "movie_id": {
    "$oid": "6818a999bca891e0fc129487"
  },
  "added_date": {
    "$date": "2025-03-19T21:09:55.497Z"
  }
},
{
  "_id": {
    "$oid": "6818a999bca891e0fc1294e7"
  },
  "user_id": {
    "$oid": "6818a997893db3ac0ac03888"
  },
  "movie_id": {
    "$oid": "6818a999bca891e0fc129482"
  },
  "added_date": {
    "$date": "2025-04-12T16:25:40.497Z"
  }
},
{
  "_id": {
    "$oid": "6818a999bca891e0fc1294e8"
  },
  "user_id": {
    "$oid": "6818a997893db3ac0ac03889"
  },
  "movie_id": {
    "$oid": "6818a999bca891e0fc129480"
  },
  "added_date": {
    "$date": "2025-03-28T22:07:19.497Z"
  }
},
{
  "_id": {
    "$oid": "6818a999bca891e0fc1294e9"
  },
  "user_id": {
    "$oid": "6818a997893db3ac0ac0388b"
  },
  "movie_id": {
    "$oid": "6818a999bca891e0fc12947f"
  },
  "added_date": {
    "$date": "2025-04-07T15:55:46.497Z"
  }
},
{
  "_id": {
    "$oid": "6818a999bca891e0fc1294ea"
  },
  "user_id": {
    "$oid": "6818a997893db3ac0ac0388b"
  },
  "movie_id": {
    "$oid": "6818a999bca891e0fc129486"
  },
  "added_date": {
    "$date": "2025-04-08T16:16:02.497Z"
  }
},
{
  "_id": {
    "$oid": "6818a999bca891e0fc1294eb"
  },
  "user_id": {
    "$oid": "6818a997893db3ac0ac0388c"
  },
  "movie_id": {
    "$oid": "6818a999bca891e0fc129487"
  },
  "added_date": {
    "$date": "2025-03-08T06:52:06.497Z"
  }
},
{
  "_id": {
    "$oid": "6818a999bca891e0fc1294ec"
  },
  "user_id": {
    "$oid": "6818a997893db3ac0ac0388c"
  },
  "movie_id": {
    "$oid": "6818a999bca891e0fc12948e"
  },
  "added_date": {
    "$date": "2025-04-12T19:48:38.497Z"
  }
},
{
  "_id": {
    "$oid": "6818a999bca891e0fc1294ed"
  },
  "user_id": {
    "$oid": "6818a997893db3ac0ac0388c"
  },
  "movie_id": {
    "$oid": "6818a999bca891e0fc129481"
  },
  "added_date": {
    "$date": "2025-03-07T13:41:56.497Z"
  }
},
{
  "_id": {
    "$oid": "6818a999bca891e0fc1294ee"
  },
  "user_id": {
    "$oid": "6818a997893db3ac0ac0388e"
  },
  "movie_id": {
    "$oid": "6818a999bca891e0fc12948c"
  },
  "added_date": {
    "$date": "2025-04-26T14:31:34.497Z"
  }
},
{
  "_id": {
    "$oid": "6818a999bca891e0fc1294ef"
  },
  "user_id": {
    "$oid": "6818a997893db3ac0ac0388e"
  },
  "movie_id": {
    "$oid": "6818a999bca891e0fc129491"
  },
  "added_date": {
    "$date": "2025-03-11T15:47:22.497Z"
  }
},
{
  "_id": {
    "$oid": "6818a999bca891e0fc1294f0"
  },
  "user_id": {
    "$oid": "6818a997893db3ac0ac0388e"
  },
  "movie_id": {
    "$oid": "6818a999bca891e0fc12948e"
  },
  "added_date": {
    "$date": "2025-03-08T16:26:05.497Z"
  }
},
{
  "_id": {
    "$oid": "6818a999bca891e0fc1294f1"
  },
  "user_id": {
    "$oid": "6818a997893db3ac0ac0388f"
  },
  "movie_id": {
    "$oid": "6818a999bca891e0fc129483"
  },
  "added_date": {
    "$date": "2025-04-03T11:18:34.497Z"
  }
},
{
  "_id": {
    "$oid": "6818a999bca891e0fc1294f2"
  },
  "user_id": {
    "$oid": "6818a997893db3ac0ac03892"
  },
  "movie_id": {
    "$oid": "6818a999bca891e0fc129484"
  },
  "added_date": {
    "$date": "2025-03-25T23:48:08.497Z"
  }
},
{
  "_id": {
    "$oid": "6818a999bca891e0fc1294f3"
  },
  "user_id": {
    "$oid": "6818a997893db3ac0ac03893"
  },
  "movie_id": {
    "$oid": "6818a999bca891e0fc129481"
  },
  "added_date": {
    "$date": "2025-04-04T23:53:11.497Z"
  }
},
{
  "_id": {
    "$oid": "6818a999bca891e0fc1294f4"
  },
  "user_id": {
    "$oid": "6818a997893db3ac0ac03893"
  },
  "movie_id": {
    "$oid": "6818a999bca891e0fc129480"
  },
  "added_date": {
    "$date": "2025-03-21T01:18:00.497Z"
  }
},
{
  "_id": {
    "$oid": "6818a999bca891e0fc1294f5"
  },
  "user_id": {
    "$oid": "6818a997893db3ac0ac03894"
  },
  "movie_id": {
    "$oid": "6818a999bca891e0fc12947f"
  },
  "added_date": {
    "$date": "2025-04-06T05:28:46.497Z"
  }
},
{
  "_id": {
    "$oid": "6818a999bca891e0fc1294f6"
  },
  "user_id": {
    "$oid": "6818a997893db3ac0ac03895"
  },
  "movie_id": {
    "$oid": "6818a999bca891e0fc129483"
  },
  "added_date": {
    "$date": "2025-04-01T03:06:38.497Z"
  }
},
{
  "_id": {
    "$oid": "6818a999bca891e0fc1294f7"
  },
  "user_id": {
    "$oid": "6818a997893db3ac0ac03895"
  },
  "movie_id": {
    "$oid": "6818a999bca891e0fc12947f"
  },
  "added_date": {
    "$date": "2025-03-28T16:23:28.497Z"
  }
},
{
  "_id": {
    "$oid": "6818a999bca891e0fc1294f8"
  },
  "user_id": {
    "$oid": "6818a997893db3ac0ac03896"
  },
  "movie_id": {
    "$oid": "6818a999bca891e0fc129491"
  },
  "added_date": {
    "$date": "2025-03-28T01:32:56.497Z"
  }
},
{
  "_id": {
    "$oid": "6818a999bca891e0fc1294f9"
  },
  "user_id": {
    "$oid": "6818a997893db3ac0ac03897"
  },
  "movie_id": {
    "$oid": "6818a999bca891e0fc129489"
  },
  "added_date": {
    "$date": "2025-03-27T07:23:12.497Z"
  }
},
{
  "_id": {
    "$oid": "6818a999bca891e0fc1294fa"
  },
  "user_id": {
    "$oid": "6818a997893db3ac0ac03897"
  },
  "movie_id": {
    "$oid": "6818a999bca891e0fc129482"
  },
  "added_date": {
    "$date": "2025-04-29T02:19:57.497Z"
  }
},
{
  "_id": {
    "$oid": "6818a999bca891e0fc1294fb"
  },
  "user_id": {
    "$oid": "6818a997893db3ac0ac03897"
  },
  "movie_id": {
    "$oid": "6818a999bca891e0fc129490"
  },
  "added_date": {
    "$date": "2025-04-24T05:15:48.497Z"
  }
},
{
  "_id": {
    "$oid": "6818a999bca891e0fc1294fc"
  },
  "user_id": {
    "$oid": "6818a997893db3ac0ac03898"
  },
  "movie_id": {
    "$oid": "6818a999bca891e0fc129483"
  },
  "added_date": {
    "$date": "2025-05-06T17:05:50.497Z"
  }
},
{
  "_id": {
    "$oid": "6818a999bca891e0fc1294fd"
  },
  "user_id": {
    "$oid": "6818a997893db3ac0ac03899"
  },
  "movie_id": {
    "$oid": "6818a999bca891e0fc12948a"
  },
  "added_date": {
    "$date": "2025-04-03T19:27:05.497Z"
  }
},
{
  "_id": {
    "$oid": "6818a999bca891e0fc1294fe"
  },
  "user_id": {
    "$oid": "6818a997893db3ac0ac03899"
  },
  "movie_id": {
    "$oid": "6818a999bca891e0fc129490"
  },
  "added_date": {
    "$date": "2025-04-27T18:42:40.497Z"
  }
},
{
  "_id": {
    "$oid": "6818a999bca891e0fc1294ff"
  },
  "user_id": {
    "$oid": "6818a997893db3ac0ac03899"
  },
  "movie_id": {
    "$oid": "6818a999bca891e0fc12948f"
  },
  "added_date": {
    "$date": "2025-03-10T03:12:15.497Z"
  }
},
{
  "_id": {
    "$oid": "6818a999bca891e0fc129500"
  },
  "user_id": {
    "$oid": "6818a997893db3ac0ac0389a"
  },
  "movie_id": {
    "$oid": "6818a999bca891e0fc129483"
  },
  "added_date": {
    "$date": "2025-04-09T20:12:52.497Z"
  }
},
{
  "_id": {
    "$oid": "6818a999bca891e0fc129501"
  },
  "user_id": {
    "$oid": "6818a997893db3ac0ac0389a"
  },
  "movie_id": {
    "$oid": "6818a999bca891e0fc12947e"
  },
  "added_date": {
    "$date": "2025-04-13T08:34:23.497Z"
  }
},
{
  "_id": {
    "$oid": "6818a999bca891e0fc129502"
  },
  "user_id": {
    "$oid": "6818a997893db3ac0ac0389a"
  },
  "movie_id": {
    "$oid": "6818a999bca891e0fc12948a"
  },
  "added_date": {
    "$date": "2025-03-15T14:03:51.497Z"
  }
},
{
  "_id": {
    "$oid": "6818a999bca891e0fc129503"
  },
  "user_id": {
    "$oid": "6818a997893db3ac0ac0389b"
  },
  "movie_id": {
    "$oid": "6818a999bca891e0fc12948f"
  },
  "added_date": {
    "$date": "2025-04-08T14:45:44.497Z"
  }
},
{
  "_id": {
    "$oid": "6818a999bca891e0fc129504"
  },
  "user_id": {
    "$oid": "6818a997893db3ac0ac0389b"
  },
  "movie_id": {
    "$oid": "6818a999bca891e0fc129484"
  },
  "added_date": {
    "$date": "2025-04-09T20:26:33.497Z"
  }
},
{
  "_id": {
    "$oid": "6818a999bca891e0fc129505"
  },
  "user_id": {
    "$oid": "6818a997893db3ac0ac0389b"
  },
  "movie_id": {
    "$oid": "6818a999bca891e0fc129483"
  },
  "added_date": {
    "$date": "2025-03-27T19:12:35.497Z"
  }
},
{
  "_id": {
    "$oid": "6818a999bca891e0fc129506"
  },
  "user_id": {
    "$oid": "6818a997893db3ac0ac0389c"
  },
  "movie_id": {
    "$oid": "6818a999bca891e0fc129490"
  },
  "added_date": {
    "$date": "2025-04-29T17:55:43.497Z"
  }
},
{
  "_id": {
    "$oid": "6818a999bca891e0fc129507"
  },
  "user_id": {
    "$oid": "6818a997893db3ac0ac0389c"
  },
  "movie_id": {
    "$oid": "6818a999bca891e0fc12948a"
  },
  "added_date": {
    "$date": "2025-04-05T12:26:36.497Z"
  }
},
{
  "_id": {
    "$oid": "6818a999bca891e0fc129508"
  },
  "user_id": {
    "$oid": "6818a997893db3ac0ac0389d"
  },
  "movie_id": {
    "$oid": "6818a999bca891e0fc12948a"
  },
  "added_date": {
    "$date": "2025-05-01T00:04:36.497Z"
  }
},
{
  "_id": {
    "$oid": "6818a999bca891e0fc129509"
  },
  "user_id": {
    "$oid": "6818a997893db3ac0ac0389e"
  },
  "movie_id": {
    "$oid": "6818a999bca891e0fc12948c"
  },
  "added_date": {
    "$date": "2025-04-21T05:25:30.497Z"
  }
},
{
  "_id": {
    "$oid": "6818a999bca891e0fc12950a"
  },
  "user_id": {
    "$oid": "6818a997893db3ac0ac0389e"
  },
  "movie_id": {
    "$oid": "6818a999bca891e0fc12948a"
  },
  "added_date": {
    "$date": "2025-03-15T03:19:38.497Z"
  }
},
{
  "_id": {
    "$oid": "6818a999bca891e0fc12950b"
  },
  "user_id": {
    "$oid": "6818a997893db3ac0ac0389f"
  },
  "movie_id": {
    "$oid": "6818a999bca891e0fc12948b"
  },
  "added_date": {
    "$date": "2025-04-30T03:59:06.497Z"
  }
},
{
  "_id": {
    "$oid": "6818a999bca891e0fc12950c"
  },
  "user_id": {
    "$oid": "6818a997893db3ac0ac0389f"
  },
  "movie_id": {
    "$oid": "6818a999bca891e0fc129481"
  },
  "added_date": {
    "$date": "2025-05-04T01:35:36.497Z"
  }
},
{
  "_id": {
    "$oid": "6818a999bca891e0fc12950d"
  },
  "user_id": {
    "$oid": "6818a997893db3ac0ac038a0"
  },
  "movie_id": {
    "$oid": "6818a999bca891e0fc12948f"
  },
  "added_date": {
    "$date": "2025-03-27T04:55:29.497Z"
  }
},
{
  "_id": {
    "$oid": "6818a999bca891e0fc12950e"
  },
  "user_id": {
    "$oid": "6818a997893db3ac0ac038a0"
  },
  "movie_id": {
    "$oid": "6818a999bca891e0fc129490"
  },
  "added_date": {
    "$date": "2025-03-10T20:19:16.497Z"
  }
},
{
  "_id": {
    "$oid": "6818a999bca891e0fc12950f"
  },
  "user_id": {
    "$oid": "6818a997893db3ac0ac038a0"
  },
  "movie_id": {
    "$oid": "6818a999bca891e0fc129482"
  },
  "added_date": {
    "$date": "2025-04-26T17:41:39.497Z"
  }
},
{
  "_id": {
    "$oid": "6818a999bca891e0fc129510"
  },
  "user_id": {
    "$oid": "6818a997893db3ac0ac038a2"
  },
  "movie_id": {
    "$oid": "6818a999bca891e0fc129491"
  },
  "added_date": {
    "$date": "2025-04-20T13:22:24.497Z"
  }
},
{
  "_id": {
    "$oid": "6818a999bca891e0fc129511"
  },
  "user_id": {
    "$oid": "6818a997893db3ac0ac038a2"
  },
  "movie_id": {
    "$oid": "6818a999bca891e0fc12948e"
  },
  "added_date": {
    "$date": "2025-04-21T21:01:38.497Z"
  }
},
{
  "_id": {
    "$oid": "6818a999bca891e0fc129512"
  },
  "user_id": {
    "$oid": "6818a997893db3ac0ac038a2"
  },
  "movie_id": {
    "$oid": "6818a999bca891e0fc12948b"
  },
  "added_date": {
    "$date": "2025-04-30T09:26:13.497Z"
  }
},
{
  "_id": {
    "$oid": "6818a999bca891e0fc129513"
  },
  "user_id": {
    "$oid": "6818a997893db3ac0ac038a3"
  },
  "movie_id": {
    "$oid": "6818a999bca891e0fc12948f"
  },
  "added_date": {
    "$date": "2025-05-05T18:48:01.497Z"
  }
},
{
  "_id": {
    "$oid": "6818a999bca891e0fc129514"
  },
  "user_id": {
    "$oid": "6818a997893db3ac0ac038a4"
  },
  "movie_id": {
    "$oid": "6818a999bca891e0fc129482"
  },
  "added_date": {
    "$date": "2025-04-23T05:18:27.497Z"
  }
},
{
  "_id": {
    "$oid": "6818a999bca891e0fc129515"
  },
  "user_id": {
    "$oid": "6818a997893db3ac0ac038a4"
  },
  "movie_id": {
    "$oid": "6818a999bca891e0fc12948b"
  },
  "added_date": {
    "$date": "2025-04-30T08:03:38.497Z"
  }
},
{
  "_id": {
    "$oid": "6818a999bca891e0fc129516"
  },
  "user_id": {
    "$oid": "6818a997893db3ac0ac038a5"
  },
  "movie_id": {
    "$oid": "6818a999bca891e0fc129491"
  },
  "added_date": {
    "$date": "2025-05-03T00:57:12.497Z"
  }
},
{
  "_id": {
    "$oid": "6818a999bca891e0fc129517"
  },
  "user_id": {
    "$oid": "6818a997893db3ac0ac038a5"
  },
  "movie_id": {
    "$oid": "6818a999bca891e0fc12948e"
  },
  "added_date": {
    "$date": "2025-03-23T21:59:45.497Z"
  }
},
{
  "_id": {
    "$oid": "6818a999bca891e0fc129518"
  },
  "user_id": {
    "$oid": "6818a997893db3ac0ac038a5"
  },
  "movie_id": {
    "$oid": "6818a999bca891e0fc129486"
  },
  "added_date": {
    "$date": "2025-04-15T12:20:41.497Z"
  }
},
{
  "_id": {
    "$oid": "6818a999bca891e0fc129519"
  },
  "user_id": {
    "$oid": "6818a997893db3ac0ac038a6"
  },
  "movie_id": {
    "$oid": "6818a999bca891e0fc129482"
  },
  "added_date": {
    "$date": "2025-05-02T16:29:40.497Z"
  }
},
{
  "_id": {
    "$oid": "6818a999bca891e0fc12951a"
  },
  "user_id": {
    "$oid": "6818a997893db3ac0ac038a6"
  },
  "movie_id": {
    "$oid": "6818a999bca891e0fc12948f"
  },
  "added_date": {
    "$date": "2025-04-13T12:46:51.497Z"
  }
},
{
  "_id": {
    "$oid": "6818a999bca891e0fc12951b"
  },
  "user_id": {
    "$oid": "6818a997893db3ac0ac038a8"
  },
  "movie_id": {
    "$oid": "6818a999bca891e0fc12948f"
  },
  "added_date": {
    "$date": "2025-03-21T06:53:19.497Z"
  }
},
{
  "_id": {
    "$oid": "6818a999bca891e0fc12951c"
  },
  "user_id": {
    "$oid": "6818a997893db3ac0ac038a9"
  },
  "movie_id": {
    "$oid": "6818a999bca891e0fc12948e"
  },
  "added_date": {
    "$date": "2025-04-22T15:25:31.497Z"
  }
},
{
  "_id": {
    "$oid": "6818a999bca891e0fc12951d"
  },
  "user_id": {
    "$oid": "6818a997893db3ac0ac038a9"
  },
  "movie_id": {
    "$oid": "6818a999bca891e0fc129491"
  },
  "added_date": {
    "$date": "2025-03-21T03:17:27.497Z"
  }
},
{
  "_id": {
    "$oid": "6818a999bca891e0fc12951e"
  },
  "user_id": {
    "$oid": "6818a997893db3ac0ac038a9"
  },
  "movie_id": {
    "$oid": "6818a999bca891e0fc12947f"
  },
  "added_date": {
    "$date": "2025-04-16T08:16:12.497Z"
  }
},
{
  "_id": {
    "$oid": "6818a999bca891e0fc12951f"
  },
  "user_id": {
    "$oid": "6818a997893db3ac0ac038aa"
  },
  "movie_id": {
    "$oid": "6818a999bca891e0fc129490"
  },
  "added_date": {
    "$date": "2025-03-26T15:28:04.497Z"
  }
},
{
  "_id": {
    "$oid": "6818a999bca891e0fc129520"
  },
  "user_id": {
    "$oid": "6818a997893db3ac0ac038aa"
  },
  "movie_id": {
    "$oid": "6818a999bca891e0fc12948e"
  },
  "added_date": {
    "$date": "2025-03-06T22:45:15.497Z"
  }
},
{
  "_id": {
    "$oid": "6818a999bca891e0fc129521"
  },
  "user_id": {
    "$oid": "6818a997893db3ac0ac038aa"
  },
  "movie_id": {
    "$oid": "6818a999bca891e0fc12948b"
  },
  "added_date": {
    "$date": "2025-04-22T03:57:43.497Z"
  }
},
{
  "_id": {
    "$oid": "6818a999bca891e0fc129522"
  },
  "user_id": {
    "$oid": "6818a997893db3ac0ac038ad"
  },
  "movie_id": {
    "$oid": "6818a999bca891e0fc12948b"
  },
  "added_date": {
    "$date": "2025-05-01T00:03:32.497Z"
  }
},
{
  "_id": {
    "$oid": "6818a999bca891e0fc129523"
  },
  "user_id": {
    "$oid": "6818a997893db3ac0ac038ad"
  },
  "movie_id": {
    "$oid": "6818a999bca891e0fc12948a"
  },
  "added_date": {
    "$date": "2025-04-10T10:00:25.497Z"
  }
},
{
  "_id": {
    "$oid": "6818a999bca891e0fc129524"
  },
  "user_id": {
    "$oid": "6818a997893db3ac0ac038ad"
  },
  "movie_id": {
    "$oid": "6818a999bca891e0fc129485"
  },
  "added_date": {
    "$date": "2025-04-16T18:34:59.497Z"
  }
},
{
  "_id": {
    "$oid": "6818a999bca891e0fc129525"
  },
  "user_id": {
    "$oid": "6818a997893db3ac0ac038ae"
  },
  "movie_id": {
    "$oid": "6818a999bca891e0fc12948c"
  },
  "added_date": {
    "$date": "2025-04-14T14:33:50.497Z"
  }
},
{
  "_id": {
    "$oid": "6818a999bca891e0fc129526"
  },
  "user_id": {
    "$oid": "6818a997893db3ac0ac038af"
  },
  "movie_id": {
    "$oid": "6818a999bca891e0fc129491"
  },
  "added_date": {
    "$date": "2025-04-28T21:44:05.497Z"
  }
},
{
  "_id": {
    "$oid": "6818a999bca891e0fc129527"
  },
  "user_id": {
    "$oid": "6818a997893db3ac0ac038b0"
  },
  "movie_id": {
    "$oid": "6818a999bca891e0fc12947f"
  },
  "added_date": {
    "$date": "2025-03-07T23:38:28.497Z"
  }
},
{
  "_id": {
    "$oid": "6818a999bca891e0fc129528"
  },
  "user_id": {
    "$oid": "6818a997893db3ac0ac038b0"
  },
  "movie_id": {
    "$oid": "6818a999bca891e0fc129482"
  },
  "added_date": {
    "$date": "2025-03-07T11:05:12.497Z"
  }
},
{
  "_id": {
    "$oid": "6818a999bca891e0fc129529"
  },
  "user_id": {
    "$oid": "6818a997893db3ac0ac038b0"
  },
  "movie_id": {
    "$oid": "6818a999bca891e0fc129480"
  },
  "added_date": {
    "$date": "2025-03-30T03:31:40.497Z"
  }
},
{
  "_id": {
    "$oid": "6818a999bca891e0fc12952a"
  },
  "user_id": {
    "$oid": "6818a997893db3ac0ac038b1"
  },
  "movie_id": {
    "$oid": "6818a999bca891e0fc12947e"
  },
  "added_date": {
    "$date": "2025-04-09T15:32:32.497Z"
  }
},
{
  "_id": {
    "$oid": "6818a999bca891e0fc12952b"
  },
  "user_id": {
    "$oid": "6818a997893db3ac0ac038b1"
  },
  "movie_id": {
    "$oid": "6818a999bca891e0fc129483"
  },
  "added_date": {
    "$date": "2025-04-13T15:54:58.497Z"
  }
},
{
  "_id": {
    "$oid": "6818a999bca891e0fc12952c"
  },
  "user_id": {
    "$oid": "6818a997893db3ac0ac038b2"
  },
  "movie_id": {
    "$oid": "6818a999bca891e0fc129482"
  },
  "added_date": {
    "$date": "2025-03-14T19:52:02.497Z"
  }
},
{
  "_id": {
    "$oid": "6818a999bca891e0fc12952d"
  },
  "user_id": {
    "$oid": "6818a997893db3ac0ac038b2"
  },
  "movie_id": {
    "$oid": "6818a999bca891e0fc129489"
  },
  "added_date": {
    "$date": "2025-04-28T19:48:13.497Z"
  }
},
{
  "_id": {
    "$oid": "6818a999bca891e0fc12952e"
  },
  "user_id": {
    "$oid": "6818a997893db3ac0ac038b2"
  },
  "movie_id": {
    "$oid": "6818a999bca891e0fc129488"
  },
  "added_date": {
    "$date": "2025-04-03T14:02:01.497Z"
  }
},
{
  "_id": {
    "$oid": "6818a999bca891e0fc12952f"
  },
  "user_id": {
    "$oid": "6818a997893db3ac0ac038b3"
  },
  "movie_id": {
    "$oid": "6818a999bca891e0fc12948d"
  },
  "added_date": {
    "$date": "2025-03-26T20:20:18.497Z"
  }
},
{
  "_id": {
    "$oid": "6818a999bca891e0fc129530"
  },
  "user_id": {
    "$oid": "6818a997893db3ac0ac038b3"
  },
  "movie_id": {
    "$oid": "6818a999bca891e0fc129488"
  },
  "added_date": {
    "$date": "2025-03-24T21:28:22.497Z"
  }
},
{
  "_id": {
    "$oid": "6818a999bca891e0fc129531"
  },
  "user_id": {
    "$oid": "6818a997893db3ac0ac038b3"
  },
  "movie_id": {
    "$oid": "6818a999bca891e0fc12948a"
  },
  "added_date": {
    "$date": "2025-03-15T14:20:16.497Z"
  }
},
{
  "_id": {
    "$oid": "6818a999bca891e0fc129532"
  },
  "user_id": {
    "$oid": "6818a997893db3ac0ac038b4"
  },
  "movie_id": {
    "$oid": "6818a999bca891e0fc129484"
  },
  "added_date": {
    "$date": "2025-04-13T11:21:05.497Z"
  }
},
{
  "_id": {
    "$oid": "6818a999bca891e0fc129533"
  },
  "user_id": {
    "$oid": "6818a997893db3ac0ac038b4"
  },
  "movie_id": {
    "$oid": "6818a999bca891e0fc129486"
  },
  "added_date": {
    "$date": "2025-04-05T20:15:35.497Z"
  }
},
{
  "_id": {
    "$oid": "6818a999bca891e0fc129534"
  },
  "user_id": {
    "$oid": "6818a997893db3ac0ac038b4"
  },
  "movie_id": {
    "$oid": "6818a999bca891e0fc129482"
  },
  "added_date": {
    "$date": "2025-04-16T12:14:59.497Z"
  }
},
{
  "_id": {
    "$oid": "6818a999bca891e0fc129535"
  },
  "user_id": {
    "$oid": "6818a997893db3ac0ac038b5"
  },
  "movie_id": {
    "$oid": "6818a999bca891e0fc129487"
  },
  "added_date": {
    "$date": "2025-04-14T15:04:35.497Z"
  }
},
{
  "_id": {
    "$oid": "6818a999bca891e0fc129536"
  },
  "user_id": {
    "$oid": "6818a997893db3ac0ac038b6"
  },
  "movie_id": {
    "$oid": "6818a999bca891e0fc129483"
  },
  "added_date": {
    "$date": "2025-04-23T13:51:34.497Z"
  }
},
{
  "_id": {
    "$oid": "6818a999bca891e0fc129537"
  },
  "user_id": {
    "$oid": "6818a997893db3ac0ac038b6"
  },
  "movie_id": {
    "$oid": "6818a999bca891e0fc129482"
  },
  "added_date": {
    "$date": "2025-05-02T03:10:47.497Z"
  }
},
{
  "_id": {
    "$oid": "6818a999bca891e0fc129538"
  },
  "user_id": {
    "$oid": "6818a997893db3ac0ac038b7"
  },
  "movie_id": {
    "$oid": "6818a999bca891e0fc12947f"
  },
  "added_date": {
    "$date": "2025-04-29T08:03:27.497Z"
  }
},
{
  "_id": {
    "$oid": "6818a999bca891e0fc129539"
  },
  "user_id": {
    "$oid": "6818a997893db3ac0ac038b8"
  },
  "movie_id": {
    "$oid": "6818a999bca891e0fc129486"
  },
  "added_date": {
    "$date": "2025-03-23T06:51:27.497Z"
  }
},
{
  "_id": {
    "$oid": "6818a999bca891e0fc12953a"
  },
  "user_id": {
    "$oid": "6818a997893db3ac0ac038b9"
  },
  "movie_id": {
    "$oid": "6818a999bca891e0fc129491"
  },
  "added_date": {
    "$date": "2025-04-02T19:00:50.497Z"
  }
}]